onenode/__init__.py
onenode/_client.py
onenode/_collection.py
onenode/_database.py
onenode/_ejson/__init__.py
onenode/_ejson/_image.py
onenode/_ejson/_models.py
onenode/_ejson/_text.py
onenode/_types.py
onenode-1.0.0.dist-info/LICENSE
onenode-1.0.0.dist-info/METADATA
onenode-1.0.0.dist-info/WHEEL
onenode-1.0.0.dist-info/RECORD
