Metadata-Version: 2.3
Name: onenode
Version: 1.0.0
Summary: OneNode Official Python Client
License: MIT
Author: Tomoh Kanazawa
Author-email: tomo@onenode.ai
Requires-Python: >=3.9,<4.0
Classifier: License :: OSI Approved :: MIT License
Classifier: Programming Language :: Python :: 3
Classifier: Programming Language :: Python :: 3.9
Classifier: Programming Language :: Python :: 3.10
Classifier: Programming Language :: Python :: 3.11
Classifier: Programming Language :: Python :: 3.12
Classifier: Programming Language :: Python :: 3.13
Requires-Dist: pymongo (>=4.11.3,<5.0.0)
Requires-Dist: requests (>=2.32.3,<3.0.0)
Project-URL: Documentation, https://docs.onenode.ai
Project-URL: Homepage, https://onenode.ai
Project-URL: Repository, https://github.com/onenodehq/onenode-py
